[
    {
        "quote": "Be yourself; everyone else is already taken.",
        "author": "Oscar Wilde"
    },
    {
        "quote": "Two things are infinite: the universe and human stupidity; and I'm not sure about the universe.",
        "author": "Albert Einstein"
    },
    {
        "quote": "So many books, so little time.",
        "author": "Frank Zappa"
    },
    {
        "quote": "A room without books is like a body without a soul.",
        "author": "Marcus Tullius Cicero"
    },
    {
        "quote": "Be the change that you wish to see in the world.",
        "author": "Mahatma Gandhi"
    },
    {
        "quote": "In three words I can sum up everything I've learned about life: it goes on.",
        "author": "Robert Frost"
    },
    {
        "quote": "If you tell the truth, you don't have to remember anything.",
        "author": "Mark Twain"
    },
    {
        "quote": "Always forgive your enemies; nothing annoys them so much.",
        "author": "Oscar Wilde"
    },
    {
        "quote": "Live as if you were to die tomorrow. Learn as if you were to live forever.",
        "author": "Mahatma Gandhi"
    },
    {
        "quote": "Without music, life would be a mistake.",
        "author": "Friedrich Nietzsche"
    },
    {
        "quote": "We accept the love we think we deserve.",
        "author": "Stephen Chbosky"
    },
    {
        "quote": "To live is the rarest thing in the world. Most people exist, that is all.",
        "author": "Oscar Wilde"
    },
    {
        "quote": "It is better to be hated for what you are than to be loved for what you are not.",
        "author": "André Gide"
    },
    {
        "quote": "Insanity is doing the same thing, over and over again, but expecting different results.",
        "author": "Narcotics Anonymous"
    },
    {
        "quote": "It does not do to dwell on dreams and forget to live.",
        "author": "J.K. Rowling"
    },
    {
        "quote": "We are all in the gutter, but some of us are looking at the stars.",
        "author": "Oscar Wilde"
    },
    {
        "quote": "Fairy tales are more than true: not because they tell us that dragons exist, but because they tell us that dragons can be beaten.",
        "author": "Neil Gaiman"
    },
    {
        "quote": "The man who does not read has no advantage over the man who cannot read.",
        "author": "Mark Twain"
    },
    {
        "quote": "I have not failed. I've just found 10,000 ways that won't work.",
        "author": "Thomas A. Edison"
    },
    {
        "quote": "It is never too late to be what you might have been.",
        "author": "George Eliot"
    },
    {
        "quote": "Everything you can imagine is real.",
        "author": "Pablo Picasso"
    },
    {
        "quote": "Success is not final, failure is not fatal: It is the courage to continue that counts.",
        "author": "Winston S. Churchill"
    },
    {
        "quote": "Do what you can, with what you have, where you are.",
        "author": "Theodore Roosevelt"
    },
    {
        "quote": "If you want to know what a man's like, take a good look at how he treats his inferiors, not his equals.",
        "author": "J.K. Rowling"
    },
    {
        "quote": "Happiness is not something ready made. It comes from your own actions.",
        "author": "Dalai Lama"
    },
    {
        "quote": "You only live once, but if you do it right, once is enough.",
        "author": "Mae West"
    },
    {
        "quote": "To be yourself in a world that is constantly trying to make you something else is the greatest accomplishment.",
        "author": "Ralph Waldo Emerson"
    },
    {
        "quote": "Do not go where the path may lead, go instead where there is no path and leave a trail.",
        "author": "Ralph Waldo Emerson"
    },
    {
        "quote": "It is our choices, Harry, that show what we truly are, far more than our abilities.",
        "author": "J.K. Rowling"
    },
    {
        "quote": "The only way to do great work is to love what you do.",
        "author": "Steve Jobs"
    },
    {
        "quote": "Be yourself; everyone else is already taken.",
        "author": "Oscar Wilde"
    },
    {
        "quote": "Two things are infinite: the universe and human stupidity; and I'm not sure about the universe.",
        "author": "Albert Einstein"
    },
    {
        "quote": "So many books, so little time.",
        "author": "Frank Zappa"
    },
    {
        "quote": "A room without books is like a body without a soul.",
        "author": "Marcus Tullius Cicero"
    },
    {
        "quote": "Be the change that you wish to see in the world.",
        "author": "Mahatma Gandhi"
    },
    {
        "quote": "In three words I can sum up everything I've learned about life: it goes on.",
        "author": "Robert Frost"
    },
    {
        "quote": "If you tell the truth, you don't have to remember anything.",
        "author": "Mark Twain"
    },
    {
        "quote": "Always forgive your enemies; nothing annoys them so much.",
        "author": "Oscar Wilde"
    },
    {
        "quote": "Live as if you were to die tomorrow. Learn as if you were to live forever.",
        "author": "Mahatma Gandhi"
    },
    {
        "quote": "Without music, life would be a mistake.",
        "author": "Friedrich Nietzsche"
    },
    {
        "quote": "We accept the love we think we deserve.",
        "author": "Stephen Chbosky"
    },
    {
        "quote": "To live is the rarest thing in the world. Most people exist, that is all.",
        "author": "Oscar Wilde"
    },
    {
        "quote": "It is better to be hated for what you are than to be loved for what you are not.",
        "author": "André Gide"
    },
    {
        "quote": "Insanity is doing the same thing, over and over again, but expecting different results.",
        "author": "Narcotics Anonymous"
    },
    {
        "quote": "It does not do to dwell on dreams and forget to live.",
        "author": "J.K. Rowling"
    },
    {
        "quote": "We are all in the gutter, but some of us are looking at the stars.",
        "author": "Oscar Wilde"
    },
    {
        "quote": "Fairy tales are more than true: not because they tell us that dragons exist, but because they tell us that dragons can be beaten.",
        "author": "Neil Gaiman"
    },
    {
        "quote": "The man who does not read has no advantage over the man who cannot read.",
        "author": "Mark Twain"
    },
    {
        "quote": "I have not failed. I've just found 10,000 ways that won't work.",
        "author": "Thomas A. Edison"
    },
    {
        "quote": "It is never too late to be what you might have been.",
        "author": "George Eliot"
    },
    {
        "quote": "Everything you can imagine is real.",
        "author": "Pablo Picasso"
    },
    {
        "quote": "Success is not final, failure is not fatal: It is the courage to continue that counts.",
        "author": "Winston S. Churchill"
    },
    {
        "quote": "Do what you can, with what you have, where you are.",
        "author": "Theodore Roosevelt"
    },
    {
        "quote": "If you want to know what a man's like, take a good look at how he treats his inferiors, not his equals.",
        "author": "J.K. Rowling"
    },
    {
        "quote": "Happiness is not something ready made. It comes from your own actions.",
        "author": "Dalai Lama"
    },
    {
        "quote": "You only live once, but if you do it right, once is enough.",
        "author": "Mae West"
    },
    {
        "quote": "To be yourself in a world that is constantly trying to make you something else is the greatest accomplishment.",
        "author": "Ralph Waldo Emerson"
    },
    {
        "quote": "Do not go where the path may lead, go instead where there is no path and leave a trail.",
        "author": "Ralph Waldo Emerson"
    },
    {
        "quote": "It is our choices, Harry, that show what we truly are, far more than our abilities.",
        "author": "J.K. Rowling"
    },
    {
        "quote": "The only way to do great work is to love what you do.",
        "author": "Steve Jobs"
    },
    {
        "quote": "Be yourself; everyone else is already taken.",
        "author": "Oscar Wilde"
    },
    {
        "quote": "Two things are infinite: the universe and human stupidity; and I'm not sure about the universe.",
        "author": "Albert Einstein"
    },
    {
        "quote": "So many books, so little time.",
        "author": "Frank Zappa"
    },
    {
        "quote": "A room without books is like a body without a soul.",
        "author": "Marcus Tullius Cicero"
    },
    {
        "quote": "Be the change that you wish to see in the world.",
        "author": "Mahatma Gandhi"
    },
    {
        "quote": "In three words I can sum up everything I've learned about life: it goes on.",
        "author": "Robert Frost"
    },
    {
        "quote": "If you tell the truth, you don't have to remember anything.",
        "author": "Mark Twain"
    },
    {
        "quote": "Always forgive your enemies; nothing annoys them so much.",
        "author": "Oscar Wilde"
    },
    {
        "quote": "Live as if you were to die tomorrow. Learn as if you were to live forever.",
        "author": "Mahatma Gandhi"
    },
    {
        "quote": "Without music, life would be a mistake.",
        "author": "Friedrich Nietzsche"
    },
    {
        "quote": "We accept the love we think we deserve.",
        "author": "Stephen Chbosky"
    },
    {
        "quote": "To live is the rarest thing in the world. Most people exist, that is all.",
        "author": "Oscar Wilde"
    },
    {
        "quote": "It is better to be hated for what you are than to be loved for what you are not.",
        "author": "André Gide"
    },
    {
        "quote": "Insanity is doing the same thing, over and over again, but expecting different results.",
        "author": "Narcotics Anonymous"
    },
    {
        "quote": "It does not do to dwell on dreams and forget to live.",
        "author": "J.K. Rowling"
    },
    {
        "quote": "We are all in the gutter, but some of us are looking at the stars.",
        "author": "Oscar Wilde"
    },
    {
        "quote": "Fairy tales are more than true: not because they tell us that dragons exist, but because they tell us that dragons can be beaten.",
        "author": "Neil Gaiman"
    },
    {
        "quote": "The man who does not read has no advantage over the man who cannot read.",
        "author": "Mark Twain"
    },
    {
        "quote": "I have not failed. I've just found 10,000 ways that won't work.",
        "author": "Thomas A. Edison"
    },
    {
        "quote": "It is never too late to be what you might have been.",
        "author": "George Eliot"
    },
    {
        "quote": "Everything you can imagine is real.",
        "author": "Pablo Picasso"
    },
    {
        "quote": "Success is not final, failure is not fatal: It is the courage to continue that counts.",
        "author": "Winston S. Churchill"
    },
    {
        "quote": "Do what you can, with what you have, where you are.",
        "author": "Theodore Roosevelt"
    },
    {
        "quote": "If you want to know what a man's like, take a good look at how he treats his inferiors, not his equals.",
        "author": "J.K. Rowling"
    },
    {
        "quote": "Happiness is not something ready made. It comes from your own actions.",
        "author": "Dalai Lama"
    },
    {
        "quote": "You only live once, but if you do it right, once is enough.",
        "author": "Mae West"
    },
    {
        "quote": "To be yourself in a world that is constantly trying to make you something else is the greatest accomplishment.",
        "author": "Ralph Waldo Emerson"
    },
    {
        "quote": "Do not go where the path may lead, go instead where there is no path and leave a trail.",
        "author": "Ralph Waldo Emerson"
    },
    {
        "quote": "It is our choices, Harry, that show what we truly are, far more than our abilities.",
        "author": "J.K. Rowling"
    },
    {
        "quote": "The only way to do great work is to love what you do.",
        "author": "Steve Jobs"
    },
    {
        "quote": "Be yourself; everyone else is already taken.",
        "author": "Oscar Wilde"
    },
    {
        "quote": "Two things are infinite: the universe and human stupidity; and I'm not sure about the universe.",
        "author": "Albert Einstein"
    },
    {
        "quote": "So many books, so little time.",
        "author": "Frank Zappa"
    },
    {
        "quote": "A room without books is like a body without a soul.",
        "author": "Marcus Tullius Cicero"
    },
    {
        "quote": "Be the change that you wish to see in the world.",
        "author": "Mahatma Gandhi"
    },
    {
        "quote": "In three words I can sum up everything I've learned about life: it goes on.",
        "author": "Robert Frost"
    },
    {
        "quote": "If you tell the truth, you don't have to remember anything.",
        "author": "Mark Twain"
    },
    {
        "quote": "Always forgive your enemies; nothing annoys them so much.",
        "author": "Oscar Wilde"
    },
    {
        "quote": "Live as if you were to die tomorrow. Learn as if you were to live forever.",
        "author": "Mahatma Gandhi"
    },
    {
        "quote": "Without music, life would be a mistake.",
        "author": "Friedrich Nietzsche"
    }
]